LICENSE
README.md
setup.py
zpybox/__init__.py
zpybox/file.py
zpybox/ip.py
zpybox/output.py
zpybox/timestamp.py
zpybox.egg-info/PKG-INFO
zpybox.egg-info/SOURCES.txt
zpybox.egg-info/dependency_links.txt
zpybox.egg-info/top_level.txt