Metadata-Version: 2.1
Name: zpybox
Version: 0.0.1
Summary: python tool box in Chinese
Home-page: UNKNOWN
Author: ZF
Author-email: zofon@qq.com
License: UNKNOWN
Keywords: tool
Platform: windows or Linux
Classifier: Development Status :: 5 - Production/Stable
Classifier: Intended Audience :: Developers
Classifier: Programming Language :: Python :: 2.7
Classifier: Programming Language :: Python :: 3.5
Classifier: Operating System :: OS Independent
Classifier: Topic :: Software Development :: Libraries :: Python Modules
Requires-Python: >=2.7.5
License-File: LICENSE
